ixlab_sshcli-0.1.2.dist-info/licenses/LICENSE
sshcli/__init__.py
sshcli/cli.py
sshcli/config.py
sshcli/models.py
sshcli/commands/__init__.py
sshcli/commands/add.py
sshcli/commands/backup.py
sshcli/commands/common.py
sshcli/commands/copy.py
sshcli/commands/edit.py
sshcli/commands/find.py
sshcli/commands/help_cmd.py
sshcli/commands/list.py
sshcli/commands/remove.py
sshcli/commands/show.py
ixlab_sshcli-0.1.2.dist-info/METADATA
ixlab_sshcli-0.1.2.dist-info/WHEEL
ixlab_sshcli-0.1.2.dist-info/entry_points.txt
ixlab_sshcli-0.1.2.dist-info/top_level.txt
ixlab_sshcli-0.1.2.dist-info/RECORD
