Metadata-Version: 2.4
Name: ixlab-sshcli
Version: 0.1.2
Summary: A tiny, modern SSH config explorer from command line.
Author-email: Iacopo Palazzi <iacopo.palazzi@gmail.com>
License: MIT
Project-URL: Homepage, https://github.com/iakko/sshcli
Keywords: ssh,config,terminal
Requires-Python: >=3.10
License-File: LICENSE
Requires-Dist: typer
Requires-Dist: rich
Dynamic: license-file
